pytorch_lightning_sam_callback/__init__.py
pytorch_lightning_sam_callback/sam.py
pytorch_lightning_sam_callback-0.1.0.dist-info/LICENSE
pytorch_lightning_sam_callback-0.1.0.dist-info/WHEEL
pytorch_lightning_sam_callback-0.1.0.dist-info/METADATA
pytorch_lightning_sam_callback-0.1.0.dist-info/RECORD
