Metadata-Version: 2.1
Name: pytorch-lightning-sam-callback
Version: 0.1.0
Summary: 
License: MIT
Author: Masahiro Wada
Author-email: argon.argon.argon@gmail.com
Requires-Python: >=3.7,<4.0
Classifier: License :: OSI Approved :: MIT License
Classifier: Programming Language :: Python :: 3
Classifier: Programming Language :: Python :: 3.7
Classifier: Programming Language :: Python :: 3.8
Classifier: Programming Language :: Python :: 3.9
Classifier: Programming Language :: Python :: 3.10
Requires-Dist: pytorch-lightning
Requires-Dist: torch
